README.rst
setup.cfg
setup.py
prose_wc/__init__.py
prose_wc/wc.py
prose_wc.egg-info/PKG-INFO
prose_wc.egg-info/SOURCES.txt
prose_wc.egg-info/dependency_links.txt
prose_wc.egg-info/entry_points.txt
prose_wc.egg-info/requires.txt
prose_wc.egg-info/top_level.txt
prose_wc/tests/__init__.py
prose_wc/tests/tests.py