Metadata-Version: 1.1
Name: prose-wc
Version: 0.3.4
Summary: Jekyll-aware prose wordcount utility
Home-page: https://github.com/makyo/prose-wc
Author: Madison Scott-Clary
Author-email: makyo@drab-makyo.com
License: UNKNOWN
Platform: UNKNOWN
Classifier: Development Status :: 4 - Beta
Classifier: Environment :: Console
Classifier: Intended Audience :: Education
Classifier: Intended Audience :: End Users/Desktop
Classifier: License :: OSI Approved :: MIT License
Classifier: Natural Language :: English
Classifier: Operating System :: OS Independent
Classifier: Topic :: Artistic Software
Classifier: Topic :: Text Processing
Classifier: Topic :: Utilities
